ipnet/__init__.py
ipnet/ipnet.py
ipnet-0.1.3.dist-info/LICENSE.txt
ipnet-0.1.3.dist-info/METADATA
ipnet-0.1.3.dist-info/WHEEL
ipnet-0.1.3.dist-info/entry_points.txt
ipnet-0.1.3.dist-info/top_level.txt
ipnet-0.1.3.dist-info/RECORD
