Metadata-Version: 2.1
Name: ipnet
Version: 0.1.3
Summary: A CLI tool for IP subnet calculation and network information. It is minimal and compact, your network info Swiss Army knife. More info at https://github.com/nicanorflavier/ipnet
Author: Nicanor II Flavier
License: GNU GENERAL PUBLIC LICENSE
Project-URL: Homepage, https://github.com/nicanorflavier/ipnet
Project-URL: Repository, https://github.com/nicanorflavier/ipnet
Project-URL: Issues, https://github.com/nicanorflavier/ipnet/issues
Project-URL: Changelog, https://github.com/nicanorflavier/ipnet/blob/master/CHANGELOG.md
Project-URL: GitHub_Statistics, https://github.com/nicanorflavier/ipnet/pulse
Project-URL: GitHub_Profile, https://github.com/nicanorflavier
Project-URL: X, https://x.com/nicanorflavier
Project-URL: Mastodon, https://mastodon.social/@nicanorflavier
Keywords: networking,ip,subnet,cli
Classifier: Programming Language :: Python :: 3
Classifier: License :: OSI Approved :: GNU General Public License v3 (GPLv3)
Classifier: Operating System :: OS Independent
Requires-Python: >=3.9
License-File: LICENSE.txt
